grafs_e/N_class.py
grafs_e/__init__.py
grafs_e/app.py
grafs_e/donnees.py
grafs_e/graphes_objet.py
grafs_e/launch.py
grafs_e/prospective.py
grafs_e/sankey.py
grafs_e/data/FAOSTAT_data_fr_vege_import.csv
grafs_e/data/FAOSTAT_data_fr_viande_import.csv
grafs_e/data/GRAFS_data.xlsx
grafs_e/data/contour-GRAFS.geojson
grafs_e/data/full_grafs.xlsx
grafs_e/data/logo.jpg
grafs_e/data/metabolism.png
grafs_e/data/projections_pop.xlsx
grafs_e/data/scenario.xlsx
grafs_e/data/scenario_region/linear/Ain-Rhône.xlsx
grafs_e/data/scenario_region/linear/Alpes.xlsx
grafs_e/data/scenario_region/linear/Alsace.xlsx
grafs_e/data/scenario_region/linear/Aveyron-Lozère.xlsx
grafs_e/data/scenario_region/linear/Bourgogne.xlsx
grafs_e/data/scenario_region/linear/Bretagne.xlsx
grafs_e/data/scenario_region/linear/Calvados-Orne.xlsx
grafs_e/data/scenario_region/linear/Cantal-Corrèze.xlsx
grafs_e/data/scenario_region/linear/Champ-Ard-Yonne.xlsx
grafs_e/data/scenario_region/linear/Côte d'Azur.xlsx
grafs_e/data/scenario_region/linear/Dor-Lot.xlsx
grafs_e/data/scenario_region/linear/Eure-et-Loir.xlsx
grafs_e/data/scenario_region/linear/Eure.xlsx
grafs_e/data/scenario_region/linear/Gard-Hérault.xlsx
grafs_e/data/scenario_region/linear/Garonne.xlsx
grafs_e/data/scenario_region/linear/Gironde.xlsx
grafs_e/data/scenario_region/linear/Grand Jura.xlsx
grafs_e/data/scenario_region/linear/Grand Marseille.xlsx
grafs_e/data/scenario_region/linear/Grande Lorraine.xlsx
grafs_e/data/scenario_region/linear/Ile de France.xlsx
grafs_e/data/scenario_region/linear/Isère-Drôme Ardèche.xlsx
grafs_e/data/scenario_region/linear/Landes.xlsx
grafs_e/data/scenario_region/linear/Loire Amont.xlsx
grafs_e/data/scenario_region/linear/Loire Centrale.xlsx
grafs_e/data/scenario_region/linear/Loire aval.xlsx
grafs_e/data/scenario_region/linear/Manche.xlsx
grafs_e/data/scenario_region/linear/Nord Pas de Calais.xlsx
grafs_e/data/scenario_region/linear/Picardie.xlsx
grafs_e/data/scenario_region/linear/Pyrénées Orient.xlsx
grafs_e-0.65.dist-info/METADATA
grafs_e-0.65.dist-info/WHEEL
grafs_e-0.65.dist-info/entry_points.txt
grafs_e-0.65.dist-info/licenses/LICENCE
grafs_e-0.65.dist-info/RECORD
