Metadata-Version: 2.4
Name: grafs_e
Version: 0.65
Summary: Metabolic analysis of Agricultural systems
Project-URL: repository, https://gricad-gitlab.univ-grenoble-alpes.fr/isterre-dynamic-modeling/grafs-e-project/grafs-e
Author-email: Adrien Fauste-Gay <adrien.fauste-gay@univ-grenoble-alpes.fr>
License:                    GNU LESSER GENERAL PUBLIC LICENSE
License-File: LICENCE
Keywords: agriculture,ecological,nitrogen,research,scientific
Classifier: Development Status :: 3 - Alpha
Classifier: Environment :: Console
Classifier: Intended Audience :: Science/Research
Classifier: License :: OSI Approved :: GNU Lesser General Public License v3 (LGPLv3)
Classifier: Operating System :: OS Independent
Classifier: Programming Language :: Python
Classifier: Programming Language :: Python :: 3.10
Classifier: Programming Language :: Python :: 3.11
Classifier: Programming Language :: Python :: 3.12
Classifier: Topic :: Scientific/Engineering
Requires-Python: >=3.10
Requires-Dist: folium>=0.19.4
Requires-Dist: ipykernel>=6.29.5
Requires-Dist: ipython>=8.34.0
Requires-Dist: matplotlib>=3.10.0
Requires-Dist: networkx>=3.4.2
Requires-Dist: openpyxl>=3.1.5
Requires-Dist: pandas>=2.2.3
Requires-Dist: plotly>=5.24.1
Requires-Dist: pulp>=2.9.0
Requires-Dist: pyomo[appsi]>=6.9.1
Requires-Dist: scipy>=1.15.2
Requires-Dist: seaborn>=0.13.2
Requires-Dist: sphinx>=8.1.3
Requires-Dist: sphinxcontrib-napoleon>=0.7
Requires-Dist: streamlit-autorefresh>=1.0.1
Requires-Dist: streamlit-folium>=0.24.0
Requires-Dist: streamlit>=1.41.1
Requires-Dist: tqdm>=4.67.1
